pyesoify/__init__.py
pyesoify/__main__.py
pyesoify/chr.py
pyesoify/esoterify.py
pyesoify/numbers.py
pyesoify/obfuscate.py
pyesoify/operators.py
pyesoify/string_factory.py
pyesoify/functions/__init__.py
pyesoify/functions/_str.py
pyesoify/functions/getattr.py
pyesoify-0.3.2.dist-info/LICENSE
pyesoify-0.3.2.dist-info/METADATA
pyesoify-0.3.2.dist-info/WHEEL
pyesoify-0.3.2.dist-info/top_level.txt
pyesoify-0.3.2.dist-info/RECORD
