Metadata-Version: 2.1
Name: pyesoify
Version: 0.3.2
Summary: A simple python package to convert python code to an esoteric form
Author-email: Tathya Garg <coding.tathya+gh@gmail.com>
License: Copyright 2024 Tathya Garg
Project-URL: Homepage, https://github.com/tathyagarg/pyesoify
Project-URL: Issues, https://github.com/tathyagarg/pyesoify/issues
Classifier: Programming Language :: Python :: 3
Classifier: License :: OSI Approved :: MIT License
Classifier: Operating System :: OS Independent
Requires-Python: >=3.9
License-File: LICENSE
